Workbook

Sheet README
A1: Family inc. — Master Operating Sheet
A2: Last updated: 2026-05-27 (added Calendar-Events tab for Phase 1)
A4: How to use this workbook
A6: 1. Upload this file to Google Drive, right-click → Open with → Google Sheets.
A7: That creates a Google Sheets version that all automations will read from.
A9: 2. Each tab is a domain. Yellow rows are SAMPLE entries — replace them with your real data, then change the cell color to white.
A11: 3. The 'Reminders' tab is the heart of the system. Every domain (Health, Car, Education, Finance, Contracts) writes its due-dates here. One daily automation reads this tab and decides whether to send a WhatsApp alert today.
A13: 4. Don't rename tabs or columns. Automations key off exact names.
A15: 5. To add a new family member, add a row in 'People' first — then reference their name elsewhere.
A17: Domain tabs
A19: People — household members, IDs, Kupot Holim, allergies
A20: Calendars — registered Google + iCloud calendars and color codes
... A43: - Account credentials should live in a password manager, not here.

Sheet People
A1: Name | B1: Role | C1: Date of Birth | D1: Teudat Zehut | E1: Kupat Holim | F1: Primary Doctor | G1: Blood Type | H1: Allergies | I1: Notes
A2: [Adar] | B2: Parent | C2: 31048 | D2: 000000000 | E2: Clalit | F2: Dr. Cohen | G2: O+ | H2: None | I2: Replace with real values
A3: [Partner] | B3: Parent | C3: 31413 | D3: 000000000 | E3: Maccabi | F3: Dr. Levi | G3: A+ | H3: Peanuts
A4: [Child 1] | B4: Child | C4: 43101 | D4: 000000000 | E4: Clalit | F4: Dr. Cohen | G4: ? | H4: None
A5: [Child 2] | B5: Child | C5: 44197 | D5: 000000000 | E5: Clalit | F5: Dr. Cohen | G5: ? | H5: Dairy

Sheet Calendars
A1: Calendar Name | B1: Source | C1: Owner | D1: Color | E1: Sync Direction | F1: Last Synced | G1: Notes
A2: [Adar — Personal] | B2: Google | C2: Adar | D2: Blue | E2: Read | G2: Primary Google calendar
A3: [Partner — Personal] | B3: iCloud | C3: Partner | D3: Pink | E3: Read (CalDAV) | G3: Use app-specific password
A4: [Family Shared] | B4: Google | C4: Both | D4: Green | E4: Read/Write | G4: Shared events live here
A5: [Kids — Preschool] | B5: Google | C5: Both | D5: Orange | E5: Read | G5: Subscribed from preschool

Sheet Calendar-Events
A1: Date | B1: Start | C1: End | D1: Title | E1: Owner | F1: Source | G1: Location | H1: Notes
A2: 46171 | B2: 19:00 | C2: 20:30 | D2: Date night | E2: Both | F2: Manual | G2: Cafe Levinsky
A3: 46176 | D3: Sunday review | E3: Both | F3: Manual | G3: Home | H3: Sunday family operating ritual
A4: 46179 | B4: 20:00 | C4: 21:30 | D4: Adar's cousin's birthday | E4: Adar | F4: iCloud | G4: Tel Aviv | H4: Bring small gift
A5: 46183 | D5: Quarterly savings transfer | E5: Adar | F5: System | G5: Reminders tab | H5: Auto-linked from Reminders row 8

Sheet Reminders
A1: Title | B1: Domain | C1: Owner | D1: Due Date | E1: Lead Times (days) | F1: Recurrence | G1: Status | H1: Last Sent | I1: Channel | J1: Notes | K1: Days until | L1: Auto-flag
A2: Car annual test (Test Rishui) | B2: Car | C2: Adar | D2: 46310 | E2: 60,30,7,1 | F2: Yearly | G2: Pending | I2: WhatsApp | J2: Plate XX-XXX-XX | K2: =IF(ISNUMBER(D2),D2-TODAY(),"") -> 141 | L2: =IF(G2="Done","",IF(NOT(ISNUMBER(D2)),"",IF(D2<TODAY(),"OVERDUE",IF(D2-TODAY()<=1,"FIRE TODAY",IF(D2-TODAY()<=7,"WEEK OUT",IF(D2-TODAY()<=30,"MONTH OUT",""))))))
A3: Car insurance renewal | B3: Car | C3: Adar | D3: 46327 | E3: 30,7,1 | F3: Yearly | G3: Pending | I3: WhatsApp | J3: Currently with Harel | K3: =IF(ISNUMBER(D3),D3-TODAY(),"") -> 158 | L3: =IF(G3="Done","",IF(NOT(ISNUMBER(D3)),"",IF(D3<TODAY(),"OVERDUE",IF(D3-TODAY()<=1,"FIRE TODAY",IF(D3-TODAY()<=7,"WEEK OUT",IF(D3-TODAY()<=30,"MONTH OUT",""))))))
A4: Dentist — Adar | B4: Health | C4: Adar | D4: 46249 | E4: 30,7 | F4: 6-month | G4: Pending | I4: WhatsApp | K4: =IF(ISNUMBER(D4),D4-TODAY(),"") -> 80 | L4: =IF(G4="Done","",IF(NOT(ISNUMBER(D4)),"",IF(D4<TODAY(),"OVERDUE",IF(D4-TODAY()<=1,"FIRE TODAY",IF(D4-TODAY()<=7,"WEEK OUT",IF(D4-TODAY()<=30,"MONTH OUT",""))))))
A5: Dentist — Child 1 | B5: Health | C5: Partner | D5: 46275 | E5: 30,7 | F5: 6-month | G5: Pending | I5: WhatsApp | K5: =IF(ISNUMBER(D5),D5-TODAY(),"") -> 106 | L5: =IF(G5="Done","",IF(NOT(ISNUMBER(D5)),"",IF(D5<TODAY(),"OVERDUE",IF(D5-TODAY()<=1,"FIRE TODAY",IF(D5-TODAY()<=7,"WEEK OUT",IF(D5-TODAY()<=30,"MONTH OUT",""))))))
A6: 1st-grade registration opens | B6: Education | C6: Both | D6: 46371 | E6: 30,14,7,1 | F6: Once | G6: Pending | I6: WhatsApp | J6: City portal | K6: =IF(ISNUMBER(D6),D6-TODAY(),"") -> 202 | L6: =IF(G6="Done","",IF(NOT(ISNUMBER(D6)),"",IF(D6<TODAY(),"OVERDUE",IF(D6-TODAY()<=1,"FIRE TODAY",IF(D6-TODAY()<=7,"WEEK OUT",IF(D6-TODAY()<=30,"MONTH OUT",""))))))
A7: Parent-teacher conference | B7: Education | C7: Both | D7: 46346 | E7: 14,3,1 | F7: Bi-yearly | G7: Pending | I7: WhatsApp | K7: =IF(ISNUMBER(D7),D7-TODAY(),"") -> 177 | L7: =IF(G7="Done","",IF(NOT(ISNUMBER(D7)),"",IF(D7<TODAY(),"OVERDUE",IF(D7-TODAY()<=1,"FIRE TODAY",IF(D7-TODAY()<=7,"WEEK OUT",IF(D7-TODAY()<=30,"MONTH OUT",""))))))
A8: Quarterly savings transfer | B8: Finance | C8: Adar | D8: 46203 | E8: 7,1 | F8: Quarterly | G8: Pending | I8: WhatsApp | J8: ₪5000 → savings | K8: =IF(ISNUMBER(D8),D8-TODAY(),"") -> 34 | L8: =IF(G8="Done","",IF(NOT(ISNUMBER(D8)),"",IF(D8<TODAY(),"OVERDUE",IF(D8-TODAY()<=1,"FIRE TODAY",IF(D8-TODAY()<=7,"WEEK OUT",IF(D8-TODAY()<=30,"MONTH OUT",""))))))
A9: Pay annual home insurance | B9: Finance | C9: Adar | D9: 46266 | E9: 14,3 | F9: Yearly | G9: Pending | I9: WhatsApp | K9: =IF(ISNUMBER(D9),D9-TODAY(),"") -> 97 | L9: =IF(G9="Done","",IF(NOT(ISNUMBER(D9)),"",IF(D9<TODAY(),"OVERDUE",IF(D9-TODAY()<=1,"FIRE TODAY",IF(D9-TODAY()<=7,"WEEK OUT",IF(D9-TODAY()<=30,"MONTH OUT",""))))))

Sheet Finance-Accts
A1: Account Name | B1: Type | C1: Bank/Provider | D1: Last 4 | E1: Owner | F1: Currency | G1: Last Imported | H1: Balance Snapshot | I1: Notes
A2: [Joint Checking] | B2: Checking | C2: Bank Hapoalim | D2: 1234 | E2: Both | F2: ILS | I2: Primary household account
A3: [Adar Savings] | B3: Savings | C3: Bank Hapoalim | D3: 5678 | E3: Adar | F3: ILS
A4: [Visa Cal — Adar] | B4: Credit Card | C4: Cal | D4: 9012 | E4: Adar | F4: ILS
A5: [Mastercard — Partner] | B5: Credit Card | C5: Isracard | D5: 3456 | E5: Partner | F5: ILS

Sheet Finance-Txns
A1: Date | B1: Account | C1: Description | D1: Amount (ILS) | E1: Category | F1: Subcategory | G1: Tags | H1: Imported From | I1: Notes
A2: 46152 | B2: [Joint Checking] | C2: SHUFERSAL DEAL | D2: -432.5 | E2: Groceries | F2: Supermarket | G2: kids | H2: hapoalim_2026-05.csv | I2: Sample row
A3: 46154 | B3: [Visa Cal — Adar] | C3: PAZ GAS STATION | D3: -280 | E3: Transport | F3: Fuel | G3: car | H3: cal_2026-05.csv
A4: 46157 | B4: [Joint Checking] | C4: MORTGAGE PAYMENT | D4: -6800 | E4: Housing | F4: Mortgage | G4: fixed | H4: hapoalim_2026-05.csv
A5: 46162 | B5: [Joint Checking] | C5: SALARY — ADAR | D5: 28500 | E5: Income | F5: Salary | G5: income | H5: hapoalim_2026-05.csv

Sheet Finance-Bdgt
A1: Category | B1: Monthly Target (ILS) | C1: Actual (current month) | D1: Variance | E1: % of Target | F1: YTD Actual | G1: Notes | H1: As-of date | I1: =TODAY() -> 46169
A2: Housing | B2: 8500 | C2: =IFERROR(-SUMIFS('Finance-Txns'!D:D,'Finance-Txns'!E:E,A2,'Finance-Txns'!A:A,">="&DATE(YEAR($I$1),MONTH($I$1),1),'Finance-Txns'!A:A,"<"&DATE(YEAR($I$1),MONTH($I$1)+1,1)),0) -> 6800 | D2: =B2-C2 -> 1700 | E2: =IFERROR(C2/B2,0) -> 0.8 | F2: =IFERROR(-SUMIFS('Finance-Txns'!D:D,'Finance-Txns'!E:E,A2,'Finance-Txns'!A:A,">="&DATE(YEAR($I$1),1,1),'Finance-Txns'!A:A,"<="&$I$1),0) -> 6800 | H2: Current month tag | I2: =TEXT(I1,"yyyy-mm") -> 2026-05
A3: Groceries | B3: 4000 | C3: =IFERROR(-SUMIFS('Finance-Txns'!D:D,'Finance-Txns'!E:E,A3,'Finance-Txns'!A:A,">="&DATE(YEAR($I$1),MONTH($I$1),1),'Finance-Txns'!A:A,"<"&DATE(YEAR($I$1),MONTH($I$1)+1,1)),0) -> 432.5 | D3: =B3-C3 -> 3567.5 | E3: =IFERROR(C3/B3,0) -> 0.108125 | F3: =IFERROR(-SUMIFS('Finance-Txns'!D:D,'Finance-Txns'!E:E,A3,'Finance-Txns'!A:A,">="&DATE(YEAR($I$1),1,1),'Finance-Txns'!A:A,"<="&$I$1),0) -> 432.5
A4: Transport | B4: 1500 | C4: =IFERROR(-SUMIFS('Finance-Txns'!D:D,'Finance-Txns'!E:E,A4,'Finance-Txns'!A:A,">="&DATE(YEAR($I$1),MONTH($I$1),1),'Finance-Txns'!A:A,"<"&DATE(YEAR($I$1),MONTH($I$1)+1,1)),0) -> 280 | D4: =B4-C4 -> 1220 | E4: =IFERROR(C4/B4,0) -> 0.18666667 | F4: =IFERROR(-SUMIFS('Finance-Txns'!D:D,'Finance-Txns'!E:E,A4,'Finance-Txns'!A:A,">="&DATE(YEAR($I$1),1,1),'Finance-Txns'!A:A,"<="&$I$1),0) -> 280
A5: Childcare | B5: 5000 | C5: =IFERROR(-SUMIFS('Finance-Txns'!D:D,'Finance-Txns'!E:E,A5,'Finance-Txns'!A:A,">="&DATE(YEAR($I$1),MONTH($I$1),1),'Finance-Txns'!A:A,"<"&DATE(YEAR($I$1),MONTH($I$1)+1,1)),0) -> 0 | D5: =B5-C5 -> 5000 | E5: =IFERROR(C5/B5,0) -> 0 | F5: =IFERROR(-SUMIFS('Finance-Txns'!D:D,'Finance-Txns'!E:E,A5,'Finance-Txns'!A:A,">="&DATE(YEAR($I$1),1,1),'Finance-Txns'!A:A,"<="&$I$1),0) -> 0
A6: Utilities | B6: 1200 | C6: =IFERROR(-SUMIFS('Finance-Txns'!D:D,'Finance-Txns'!E:E,A6,'Finance-Txns'!A:A,">="&DATE(YEAR($I$1),MONTH($I$1),1),'Finance-Txns'!A:A,"<"&DATE(YEAR($I$1),MONTH($I$1)+1,1)),0) -> 0 | D6: =B6-C6 -> 1200 | E6: =IFERROR(C6/B6,0) -> 0 | F6: =IFERROR(-SUMIFS('Finance-Txns'!D:D,'Finance-Txns'!E:E,A6,'Finance-Txns'!A:A,">="&DATE(YEAR($I$1),1,1),'Finance-Txns'!A:A,"<="&$I$1),0) -> 0
A7: Health | B7: 800 | C7: =IFERROR(-SUMIFS('Finance-Txns'!D:D,'Finance-Txns'!E:E,A7,'Finance-Txns'!A:A,">="&DATE(YEAR($I$1),MONTH($I$1),1),'Finance-Txns'!A:A,"<"&DATE(YEAR($I$1),MONTH($I$1)+1,1)),0) -> 0 | D7: =B7-C7 -> 800 | E7: =IFERROR(C7/B7,0) -> 0 | F7: =IFERROR(-SUMIFS('Finance-Txns'!D:D,'Finance-Txns'!E:E,A7,'Finance-Txns'!A:A,">="&DATE(YEAR($I$1),1,1),'Finance-Txns'!A:A,"<="&$I$1),0) -> 0
A8: Entertainment | B8: 800 | C8: =IFERROR(-SUMIFS('Finance-Txns'!D:D,'Finance-Txns'!E:E,A8,'Finance-Txns'!A:A,">="&DATE(YEAR($I$1),MONTH($I$1),1),'Finance-Txns'!A:A,"<"&DATE(YEAR($I$1),MONTH($I$1)+1,1)),0) -> 0 | D8: =B8-C8 -> 800 | E8: =IFERROR(C8/B8,0) -> 0 | F8: =IFERROR(-SUMIFS('Finance-Txns'!D:D,'Finance-Txns'!E:E,A8,'Finance-Txns'!A:A,">="&DATE(YEAR($I$1),1,1),'Finance-Txns'!A:A,"<="&$I$1),0) -> 0
A9: Dining out | B9: 1000 | C9: =IFERROR(-SUMIFS('Finance-Txns'!D:D,'Finance-Txns'!E:E,A9,'Finance-Txns'!A:A,">="&DATE(YEAR($I$1),MONTH($I$1),1),'Finance-Txns'!A:A,"<"&DATE(YEAR($I$1),MONTH($I$1)+1,1)),0) -> 0 | D9: =B9-C9 -> 1000 | E9: =IFERROR(C9/B9,0) -> 0 | F9: =IFERROR(-SUMIFS('Finance-Txns'!D:D,'Finance-Txns'!E:E,A9,'Finance-Txns'!A:A,">="&DATE(YEAR($I$1),1,1),'Finance-Txns'!A:A,"<="&$I$1),0) -> 0
A10: Subscriptions | B10: 400 | C10: =IFERROR(-SUMIFS('Finance-Txns'!D:D,'Finance-Txns'!E:E,A10,'Finance-Txns'!A:A,">="&DATE(YEAR($I$1),MONTH($I$1),1),'Finance-Txns'!A:A,"<"&DATE(YEAR($I$1),MONTH($I$1)+1,1)),0) -> 0 | D10: =B10-C10 -> 400 | E10: =IFERROR(C10/B10,0) -> 0 | F10: =IFERROR(-SUMIFS('Finance-Txns'!D:D,'Finance-Txns'!E:E,A10,'Finance-Txns'!A:A,">="&DATE(YEAR($I$1),1,1),'Finance-Txns'!A:A,"<="&$I$1),0) -> 0
A11: Savings | B11: 5000 | C11: =IFERROR(-SUMIFS('Finance-Txns'!D:D,'Finance-Txns'!E:E,A11,'Finance-Txns'!A:A,">="&DATE(YEAR($I$1),MONTH($I$1),1),'Finance-Txns'!A:A,"<"&DATE(YEAR($I$1),MONTH($I$1)+1,1)),0) -> 0 | D11: =B11-C11 -> 5000 | E11: =IFERROR(C11/B11,0) -> 0 | F11: =IFERROR(-SUMIFS('Finance-Txns'!D:D,'Finance-Txns'!E:E,A11,'Finance-Txns'!A:A,">="&DATE(YEAR($I$1),1,1),'Finance-Txns'!A:A,"<="&$I$1),0) -> 0
A12: Other | B12: 500 | C12: =IFERROR(-SUMIFS('Finance-Txns'!D:D,'Finance-Txns'!E:E,A12,'Finance-Txns'!A:A,">="&DATE(YEAR($I$1),MONTH($I$1),1),'Finance-Txns'!A:A,"<"&DATE(YEAR($I$1),MONTH($I$1)+1,1)),0) -> 0 | D12: =B12-C12 -> 500 | E12: =IFERROR(C12/B12,0) -> 0 | F12: =IFERROR(-SUMIFS('Finance-Txns'!D:D,'Finance-Txns'!E:E,A12,'Finance-Txns'!A:A,">="&DATE(YEAR($I$1),1,1),'Finance-Txns'!A:A,"<="&$I$1),0) -> 0
A13: TOTAL | B13: =SUM(B2:B12) -> 28700 | C13: =SUM(C2:C12) -> 7512.5 | D13: =B13-C13 -> 21187.5 | E13: =IFERROR(C13/B13,0) -> 0.26175958 | F13: =SUM(F2:F12) -> 7512.5

Sheet Goals
A1: Goal | B1: Owner | C1: Horizon | D1: Target Date | E1: 90-Day Milestone | F1: % Complete | G1: Last Update | H1: Status | I1: Notes
A2: [Buy a home in the Center] | B2: Both | C2: 3 years | D2: 47239 | E2: Open dedicated savings account + 30k₪ in | F2: 5 | G2: 46167 | H2: On track | I2: Need partner alignment on neighborhood
A3: [60k₪ emergency fund] | B3: Adar | C3: 1 year | D3: 46508 | E3: Reach 20k₪ | F3: 20 | G3: 46167 | H3: On track
A4: [Career: lead larger team] | B4: Partner | C4: 2 years | D4: 46874 | E4: Take internal management course | F4: 0 | G4: 46167 | H4: Not started

Sheet Education
A1: Child | B1: Institution | C1: Year/Grade | D1: Teacher/Caregiver | E1: Next Key Date | F1: Type | G1: Action Needed | H1: Contact | I1: Notes
A2: [Child 1] | B2: [Preschool name] | C2: Gan Trom-Hova | D2: [Teacher] | E2: 46266 | F2: School year start | G2: Buy supplies, label clothes | H2: [teacher@school]
A3: [Child 1] | B3: [Preschool name] | C3: Gan Trom-Hova | D3: [Teacher] | E3: 46346 | F3: Parent-teacher | G3: Schedule meeting slot | H3: [teacher@school]
A4: [Child 2] | B4: [Daycare name] | C4: Maon | D4: [Caregiver] | E4: 46371 | F4: 1st-grade registration opens | G4: Register on city portal | H4: [city helpdesk] | I4: Adar to lead

Sheet Health
A1: Person | B1: Provider | C1: Specialty | D1: Last Visit | E1: Next Due | F1: Frequency | G1: Action Needed | H1: Contact | I1: Notes
A2: [Adar] | B2: Dr. Cohen — Clalit | C2: Family doctor | D2: 46032 | E2: 46397 | F2: Yearly | G2: Schedule annual check | H2: [clinic phone]
A3: [Adar] | B3: Dr. Stern | C3: Dentist | D3: 46068 | E3: 46249 | F3: 6-month | G3: Schedule cleaning | H3: [clinic phone]
A4: [Partner] | B4: Dr. Levi — Maccabi | C4: Family doctor | D4: 45966 | E4: 46331 | F4: Yearly | H4: [clinic phone]
A5: [Child 1] | B5: Dr. Cohen — Clalit | C5: Pediatrician | D5: 46101 | E5: 46285 | F5: 6-month | G5: Routine check | H5: [clinic phone]
A6: [Child 1] | B6: Tipat Halav | C6: Vaccines | D6: 46113 | E6: 46296 | F6: Per schedule | G6: MMR booster | H6: [Tipat Halav phone]
A7: [Child 2] | B7: Tipat Halav | C7: Vaccines | D7: 46063 | E7: 46244 | F7: Per schedule | G7: 12-month vaccines | H7: [Tipat Halav phone]

Sheet Car
A1: Vehicle | B1: Plate | C1: Owner | D1: Annual Test (Rishui) | E1: Insurance Renewal | F1: Insurance Provider | G1: License Expiry | H1: Mechanic | I1: Notes
A2: [Make/Model — Year] | B2: [XX-XXX-XX] | C2: Adar | D2: 46310 | E2: 46327 | F2: Harel | G2: 47557 | H2: [Mechanic shop] | I2: Last service date in notes

Sheet Contacts
A1: Name | B1: Role | C1: Phone | D1: Email | E1: Linked Domain | F1: Notes
A2: Dr. Cohen | B2: Family doctor — Clalit | C2: [phone] | D2: [email] | E2: Health | F2: First call for Adar + kids
A3: [Mechanic name] | B3: Auto mechanic | C3: [phone] | E3: Car
A4: [Teacher name] | B4: Preschool teacher | C4: [phone] | D4: [email] | E4: Education | F4: Child 1 preschool
A5: [Insurance agent] | B5: Home + car insurance | C5: [phone] | D5: [email] | E5: Contracts | F5: Harel agent
A6: [Accountant name] | B6: Family accountant | C6: [phone] | D6: [email] | E6: Finance

Sheet Contracts
A1: Contract | B1: Provider | C1: Type | D1: Start Date | E1: Renewal Date | F1: Monthly Cost (ILS) | G1: Annual Cost (ILS) | H1: Auto-Renew | I1: Notes
A2: [Mortgage] | B2: Bank Hapoalim | C2: Mortgage | D2: 45444 | E2: — | F2: 6800 | G2: 81600 | H2: Yes | I2: 30-year fixed
A3: [Home insurance] | B3: Harel | C3: Insurance | D3: 45901 | E3: 46266 | F3: 320 | G3: 3840 | H3: Yes
A4: [Car insurance] | B4: Harel | C4: Insurance | D4: 45962 | E4: 46327 | F4: 580 | G4: 6960 | H4: No | I4: Shop around each year
A5: [Electricity] | B5: IEC | C5: Utility | D5: — | E5: — | F5: 550 | G5: 6600 | H5: Yes | I5: Estimated avg
A6: [Internet] | B6: Bezeq | C6: Utility | D6: 45658 | E6: 46388 | F6: 99 | G6: 1188 | H6: Yes
A7: [Mobile — Adar] | B7: Pelephone | C7: Utility | D7: — | E7: — | F7: 49 | G7: 588 | H7: Yes

Sheet Lists
A1: Controlled vocabularies — edit here, dropdowns update everywhere.
A2: Domain | B2: Owner | C2: Status | D2: Channel | E2: Recurrence | F2: Currency | G2: AcctType | H2: SyncDir | I2: Horizon | J2: GoalStatus | K2: BudgetCat | L2: ContractType | M2: AutoRenew | N2: BloodType | O2: Kupat
A3: Calendar | B3: Adar | C3: Pending | D3: WhatsApp | E3: One-off | F3: ILS | G3: Checking | H3: Read | I3: 3 months | J3: Not started | K3: Housing | L3: Mortgage | M3: Yes | N3: A+ | O3: Clalit
A4: Finance | B4: Partner | C4: Snoozed | D4: Email | E4: Daily | F4: USD | G4: Savings | H4: Write | I4: 6 months | J4: On track | K4: Groceries | L4: Rent | M4: No | N4: A- | O4: Maccabi
A5: Goals | B5: Both | C5: Sent | D5: None | E5: Weekly | F5: EUR | G5: Credit Card | H5: Read-Write | I5: 1 year | J5: At risk | K5: Utilities | L5: Insurance | M5: Unknown | N5: B+ | O5: Meuhedet
A6: Education | B6: Child 1 | C6: Done | E6: Monthly | F6: GBP | G6: Investment | H6: Disabled | I6: 3 years | J6: Blocked | K6: Transport | L6: Utility | N6: B- | O6: Leumit
A7: Health | B7: Child 2 | C7: Skipped | E7: Quarterly | G7: Loan | I7: 5 years | J7: Done | K7: Childcare | L7: Subscription | N7: O+ | O7: Other
A8: Car | B8: System | C8: Overdue | E8: Yearly | G8: Other | I8: 10+ years | J8: Paused | K8: Education | L8: Telecom | N8: O-
A9: Contacts | E9: Custom | K9: Health | L9: Other | N9: AB+
A10: Contracts | K10: Dining out | N10: AB-
A11: People | K11: Entertainment | N11: Unknown
A12: Other | K12: Clothing
K13: Travel
K14: Insurance
K15: Subscriptions
K16: Gifts
K17: Savings
K18: Other
